LICENSE
MANIFEST.in
README.rst
requirements.txt
setup.py
djangorestframework_custom_filters.egg-info/PKG-INFO
djangorestframework_custom_filters.egg-info/SOURCES.txt
djangorestframework_custom_filters.egg-info/dependency_links.txt
djangorestframework_custom_filters.egg-info/pbr.json
djangorestframework_custom_filters.egg-info/requires.txt
djangorestframework_custom_filters.egg-info/top_level.txt
rest_framework_custom_filters/__init__.py
rest_framework_custom_filters/filters.py