Metadata-Version: 1.1
Name: djangorestframework-custom-filters
Version: 1.0.0
Summary: Custom filters for Django REST Framework
Home-page: https://github.com/unistra/django-rest-framework-custom-filters
Author: Morgan Bohn
Author-email: morgan.bohn@unistra.fr
License: UNKNOWN
Download-URL: https://pypi.python.org/pypi/djangorestframework-custom-filters
Keywords: django,REST,rest_framework,filters
Platform: UNKNOWN
Classifier: Development Status :: 4 - Beta
Classifier: Environment :: Web Environment
Classifier: Framework :: Django
Classifier: Intended Audience :: Developers
Classifier: License :: OSI Approved :: GNU General Public License v2 (GPLv2)
Classifier: Programming Language :: Python :: 2.7
Classifier: Programming Language :: Python :: 3
